{"comments": {}, "page": {"body": {"container": {"style": {"background-color": "#bdd6c4"}}, "content": {"computedStyle": {"linkColor": "#b21420", "messageBackgroundColor": "#f3f3f3", "messageWidth": "630px"}, "style": {"color": "#000000", "font-family": "Nunito, Arial, Helvetica Neue, Helvetica, sans-serif"}}, "type": "mailup-bee-page-properties", "webFonts": [{"fontFamily": "'Nunito', Arial, 'Helvetica Neue', Helvetica, sans-serif", "name": "Nunito", "url": "https://fonts.googleapis.com/css?family=Nunito"}]}, "description": "", "rows": [{"columns": [{"grid-columns": 12, "modules": [{"descriptor": {"computedStyle": {"class": "center autowidth", "width": "108px"}, "image": {"alt": "Logo", "height": "66px", "href": "", "prefix": "", "src": "https://d1oco4z2z1fhwp.cloudfront.net/templates/default/5706/LOGO-02-02.png", "target": "_self", "width": "108px"}, "style": {"padding-bottom": "10px", "padding-left": "10px", "padding-right": "10px", "padding-top": "10px", "width": "100%"}}, "locked": false, "type": "mailup-bee-newsletter-modules-image", "uuid": "ebb6b5f0-603a-45f1-a66b-f94d527be4ef"}], "style": {"background-color": "transparent", "border-bottom": "0px solid transparent", "border-left": "0px solid transparent", "border-right": "0px solid transparent", "border-top": "0px solid transparent", "padding-bottom": "5px", "padding-left": "0px", "padding-right": "0px", "padding-top": "5px"}, "uuid": "ac370532-0eac-42a8-b11b-3624e562cef3"}], "container": {"style": {"background-color": "transparent", "background-image": "none", "background-position": "top left", "background-repeat": "no-repeat"}}, "content": {"computedStyle": {"hideContentOnDesktop": false, "hideContentOnMobile": false, "rowColStackOnMobile": true, "rowReverseColStackOnMobile": false, "verticalAlign": "top"}, "style": {"background-color": "#f3f3f3", "background-image": "none", "background-position": "top left", "background-repeat": "no-repeat", "color": "#000000", "width": "630px"}}, "empty": false, "locked": false, "synced": false, "type": "one-column-empty", "uuid": "e1ea3bc5-9b6a-4f5c-826f-64ee95646dc4"}, {"columns": [{"grid-columns": 12, "modules": [{"descriptor": {"computedStyle": {"hideContentOnAmp": false, "hideContentOnDesktop": false, "hideContentOnHtml": false, "hideContentOnMobile": false}, "paragraph": {"computedStyle": {"linkColor": "#f3f3f3"}, "html": "<p style=\"word-break:break-word;\"><span>FREE SHIPPING ON ORDERS OVER $300</span></p>", "style": {"color": "#ffffff", "font-family": "'Nunito',Arial,'Helvetica Neue',Helvetica,sans-serif", "font-size": "12px", "letter-spacing": "1px", "line-height": "120%", "text-align": "center"}}, "style": {"padding-bottom": "7px", "padding-left": "15px", "padding-right": "15px", "padding-top": "7px"}}, "locked": false, "type": "mailup-bee-newsletter-modules-paragraph", "uuid": "edcb444f-e579-4882-bb35-b59bf6613bf9"}], "style": {"background-color": "transparent", "border-bottom": "0px solid transparent", "border-left": "0px solid transparent", "border-right": "0px solid transparent", "border-top": "0px solid transparent", "padding-bottom": "0px", "padding-left": "0px", "padding-right": "0px", "padding-top": "0px"}, "uuid": "ed0212fc-7a2a-4e4e-a001-ceb3d495df2a"}], "container": {"style": {"background-color": "transparent", "background-image": "none", "background-position": "top left", "background-repeat": "no-repeat"}}, "content": {"computedStyle": {"hideContentOnDesktop": false, "hideContentOnMobile": false, "rowColStackOnMobile": true, "rowReverseColStackOnMobile": false, "verticalAlign": "top"}, "style": {"background-color": "#005e26", "background-image": "none", "background-position": "top left", "background-repeat": "no-repeat", "color": "#000000", "width": "630px"}}, "empty": false, "locked": false, "synced": false, "type": "one-column-empty", "uuid": "cc6a56d7-e48f-4a3a-8b41-b828070ee465"}, {"columns": [{"grid-columns": 12, "modules": [{"descriptor": {"computedStyle": {"class": "center autowidth", "hideContentOnMobile": false, "width": "630px"}, "image": {"alt": "Sweater and coffee", "height": "733px", "href": "", "prefix": "", "src": "https://d1oco4z2z1fhwp.cloudfront.net/templates/default/5706/STAMP-01-01.png", "target": "_self", "width": "650px"}, "style": {"padding-bottom": "10px", "padding-left": "0px", "padding-right": "0px", "padding-top": "0px", "width": "100%"}}, "locked": false, "type": "mailup-bee-newsletter-modules-image", "uuid": "ee3e5695-05ce-4956-9d86-2ab004c9ec5b"}, {"descriptor": {"computedStyle": {"height": 42, "width": 52}, "heading": {"style": {"color": "#005e26", "direction": "ltr", "font-family": "'Nunito', Arial, 'Helvetica Neue', Helvetica, sans-serif", "font-size": "18px", "font-weight": "normal", "letter-spacing": "1px", "line-height": "120%", "link-color": "#E01253", "text-align": "center"}, "text": "'TIS THE SEASON", "title": "h1"}, "style": {"padding-bottom": "5px", "padding-left": "15px", "padding-right": "15px", "padding-top": "35px", "text-align": "center", "width": "100%"}}, "locked": false, "type": "mailup-bee-newsletter-modules-heading", "uuid": "e3527beb-fefe-4ba8-a5c2-de6766726d0b"}, {"descriptor": {"computedStyle": {"height": 42, "width": 52}, "heading": {"style": {"color": "#b21420", "direction": "ltr", "font-family": "'Nunito', Arial, 'Helvetica Neue', Helvetica, sans-serif", "font-size": "34px", "font-weight": "normal", "letter-spacing": "1px", "line-height": "120%", "link-color": "#E01253", "text-align": "center"}, "text": "UGLY SWEATERS", "title": "h1"}, "style": {"padding-bottom": "10px", "padding-left": "15px", "padding-right": "15px", "padding-top": "0px", "text-align": "center", "width": "100%"}}, "locked": false, "type": "mailup-bee-newsletter-modules-heading", "uuid": "44e0ee9c-1164-41c5-8552-128be169c178"}, {"descriptor": {"button": {"href": "example.com", "label": "<div class=\"txtTinyMce-wrapper\" style=\"\" data-mce-style=\"\"><p style=\"word-break:break-word;\" data-mce-style=\"word-break:break-word;\"><span style=\"\" data-mce-style=\"\"><strong>SHOP NOW</strong></span></p></div>", "style": {"background-color": "transparent", "border-bottom": "2px solid #B21420", "border-left": "2px solid #B21420", "border-radius": "0px", "border-right": "2px solid #B21420", "border-top": "2px solid #B21420", "color": "#b21420", "direction": "ltr", "font-family": "inherit", "font-size": "14px", "line-height": "180%", "max-width": "100%", "padding-bottom": "3px", "padding-left": "40px", "padding-right": "40px", "padding-top": "3px", "width": "auto"}, "target": "_self"}, "computedStyle": {"height": 38, "hideContentOnMobile": false, "width": 164}, "style": {"padding-bottom": "10px", "padding-left": "10px", "padding-right": "10px", "padding-top": "10px", "text-align": "center"}}, "locked": false, "type": "mailup-bee-newsletter-modules-button", "uuid": "bbd6cf24-84dd-4e8f-a815-9b4f10aa6fcd"}, {"descriptor": {"computedStyle": {"hideContentOnMobile": false}, "spacer": {"style": {"height": "60px"}}}, "locked": false, "type": "mailup-bee-newsletter-modules-spacer", "uuid": "5819745f-efa1-4eff-aefa-b6200c9771c2"}], "style": {"background-color": "transparent", "border-bottom": "0px solid transparent", "border-left": "0px solid transparent", "border-right": "0px solid transparent", "border-top": "0px solid transparent", "padding-bottom": "0px", "padding-left": "0px", "padding-right": "0px", "padding-top": "0px"}, "uuid": "ac370532-0eac-42a8-b11b-3624e562cef3"}], "container": {"style": {"background-color": "transparent", "background-image": "none", "background-position": "top left", "background-repeat": "no-repeat"}}, "content": {"computedStyle": {"hideContentOnDesktop": false, "hideContentOnMobile": false, "rowColStackOnMobile": true, "rowReverseColStackOnMobile": false, "verticalAlign": "top"}, "style": {"background-color": "#f3f3f3", "background-image": "none", "background-position": "top left", "background-repeat": "no-repeat", "color": "#000000", "width": "630px"}}, "empty": false, "locked": false, "synced": false, "type": "one-column-empty", "uuid": "7c1fb6d8-cf3b-4fc5-96e6-5589d489dacb"}, {"columns": [{"grid-columns": 12, "modules": [{"descriptor": {"computedStyle": {"class": "center fixedwidth fullwidthOnMobile", "width": "598.5px"}, "image": {"alt": "Christmas pattern", "height": "94px", "href": "", "prefix": "", "src": "https://d1oco4z2z1fhwp.cloudfront.net/templates/default/5706/PATTERN-03.png", "target": "_self", "width": "877px"}, "style": {"padding-bottom": "0px", "padding-left": "0px", "padding-right": "0px", "padding-top": "0px", "width": "100%"}}, "locked": false, "type": "mailup-bee-newsletter-modules-image", "uuid": "c27258f8-70fd-41e1-9e70-fc0a63dab225"}], "style": {"background-color": "transparent", "border-bottom": "0px solid transparent", "border-left": "0px solid transparent", "border-right": "0px solid transparent", "border-top": "0px solid transparent", "padding-bottom": "10px", "padding-left": "0px", "padding-right": "0px", "padding-top": "10px"}, "uuid": "e021c6b3-9b04-46e2-9160-21d33f4377dd"}], "container": {"style": {"background-color": "transparent", "background-image": "none", "background-position": "top left", "background-repeat": "no-repeat"}}, "content": {"computedStyle": {"hideContentOnDesktop": false, "hideContentOnMobile": false, "rowColStackOnMobile": true, "rowReverseColStackOnMobile": false, "verticalAlign": "top"}, "style": {"background-color": "#0a5029", "background-image": "none", "background-position": "top left", "background-repeat": "no-repeat", "color": "#000000", "width": "630px"}}, "empty": false, "locked": false, "synced": false, "type": "one-column-empty", "uuid": "eb077401-1f3e-4f06-b085-5eb92516fa43"}, {"columns": [{"grid-columns": 12, "modules": [{"descriptor": {"computedStyle": {"height": 42, "width": 52}, "heading": {"style": {"color": "#b21420", "direction": "ltr", "font-family": "'Nunito', Arial, 'Helvetica Neue', Helvetica, sans-serif", "font-size": "20px", "font-weight": "normal", "letter-spacing": "1px", "line-height": "120%", "link-color": "#b21420", "text-align": "center"}, "text": "<strong>OUR BEST-SELLERS</strong>", "title": "h1"}, "style": {"padding-bottom": "10px", "padding-left": "30px", "padding-right": "30px", "padding-top": "40px", "text-align": "center", "width": "100%"}}, "locked": false, "type": "mailup-bee-newsletter-modules-heading", "uuid": "7d89835f-56e5-4d25-9e0c-c695ce18a818"}], "style": {"background-color": "transparent", "border-bottom": "0px solid transparent", "border-left": "0px solid transparent", "border-right": "0px solid transparent", "border-top": "0px solid transparent", "padding-bottom": "5px", "padding-left": "0px", "padding-right": "0px", "padding-top": "5px"}, "uuid": "2265159f-8fed-435e-92b6-2eb5a3856a7a"}], "container": {"style": {"background-color": "transparent", "background-image": "none", "background-position": "top left", "background-repeat": "no-repeat"}}, "content": {"computedStyle": {"hideContentOnDesktop": false, "hideContentOnMobile": false, "rowColStackOnMobile": true, "rowReverseColStackOnMobile": false, "verticalAlign": "top"}, "style": {"background-color": "#f3f3f3", "background-image": "none", "background-position": "top left", "background-repeat": "no-repeat", "color": "#000000", "width": "630px"}}, "empty": false, "locked": false, "synced": false, "type": "one-column-empty", "uuid": "5bc73ef0-4646-49b7-a8ea-52d361baeb0d"}, {"columns": [{"grid-columns": 4, "modules": [{"descriptor": {"computedStyle": {"class": "center fixedwidth fullwidthOnMobile", "width": "170px"}, "image": {"alt": "Product", "height": "340px", "href": "", "prefix": "", "src": "https://d1oco4z2z1fhwp.cloudfront.net/templates/default/5706/AdobeStock_309361881_edited.jpg", "target": "_self", "width": "300px"}, "style": {"padding-bottom": "20px", "padding-left": "20px", "padding-right": "20px", "padding-top": "20px", "width": "100%"}}, "locked": false, "type": "mailup-bee-newsletter-modules-image", "uuid": "2c4f8171-bbd2-4dfa-8de4-524f288092aa"}, {"descriptor": {"computedStyle": {"hideContentOnAmp": false, "hideContentOnDesktop": false, "hideContentOnHtml": false, "hideContentOnMobile": false}, "paragraph": {"computedStyle": {"linkColor": "#8a3b8f"}, "html": "<p style=\"word-break:break-word;\"><span><strong>NAVY SNOWFLAKE SWEATER</strong></span></p>", "style": {"color": "#393d47", "font-family": "inherit", "font-size": "15px", "letter-spacing": "0px", "line-height": "120%", "text-align": "center"}}, "style": {"padding-bottom": "0px", "padding-left": "15px", "padding-right": "15px", "padding-top": "10px"}}, "locked": false, "type": "mailup-bee-newsletter-modules-paragraph", "uuid": "7ae36bf8-efee-40ce-a7c4-7e276e42222e"}, {"descriptor": {"computedStyle": {"hideContentOnAmp": false, "hideContentOnDesktop": false, "hideContentOnHtml": false, "hideContentOnMobile": false}, "paragraph": {"computedStyle": {"linkColor": "#8a3b8f"}, "html": "<p style=\"word-break:break-word;\"><span>Lorem impsum at</span></p>", "style": {"color": "#393d47", "font-family": "inherit", "font-size": "15px", "letter-spacing": "0px", "line-height": "120%", "text-align": "center"}}, "style": {"padding-bottom": "10px", "padding-left": "15px", "padding-right": "15px", "padding-top": "3px"}}, "locked": false, "type": "mailup-bee-newsletter-modules-paragraph", "uuid": "2dafa43e-b955-4a5d-afe1-aaf1eb75ee49"}, {"descriptor": {"button": {"href": "example.com", "label": "<div class=\"txtTinyMce-wrapper\" style=\"\" data-mce-style=\"\"><p style=\"word-break:break-word;\" data-mce-style=\"word-break:break-word;\"><span style=\"\" data-mce-style=\"\"><strong>SHOP NOW</strong></span></p></div>", "style": {"background-color": "transparent", "border-bottom": "2px solid #B21420", "border-left": "2px solid #B21420", "border-radius": "0px", "border-right": "2px solid #B21420", "border-top": "2px solid #B21420", "color": "#b21420", "direction": "ltr", "font-family": "inherit", "font-size": "12px", "line-height": "150%", "max-width": "100%", "padding-bottom": "3px", "padding-left": "20px", "padding-right": "20px", "padding-top": "3px", "width": "auto"}, "target": "_self"}, "computedStyle": {"height": 34, "hideContentOnMobile": false, "width": 112}, "style": {"padding-bottom": "10px", "padding-left": "10px", "padding-right": "10px", "padding-top": "10px", "text-align": "center"}}, "locked": false, "type": "mailup-bee-newsletter-modules-button", "uuid": "02e14981-96ed-43ec-a4fc-7bb880d89bec"}], "style": {"background-color": "transparent", "border-bottom": "0px solid transparent", "border-left": "0px solid transparent", "border-right": "0px solid transparent", "border-top": "0px solid transparent", "padding-bottom": "0px", "padding-left": "0px", "padding-right": "0px", "padding-top": "0px"}, "uuid": "674a2acb-aa03-411e-ae35-b564dcae1219"}, {"grid-columns": 4, "modules": [{"descriptor": {"computedStyle": {"class": "center fixedwidth fullwidthOnMobile", "width": "170px"}, "image": {"alt": "Product", "height": "340px", "href": "", "prefix": "", "src": "https://d1oco4z2z1fhwp.cloudfront.net/templates/default/5706/AdobeStock_309762980_edit.jpg", "target": "_self", "width": "300px"}, "style": {"padding-bottom": "20px", "padding-left": "20px", "padding-right": "20px", "padding-top": "20px", "width": "100%"}}, "locked": false, "type": "mailup-bee-newsletter-modules-image", "uuid": "97cc242f-8042-494c-a801-a5fa34a990d3"}, {"descriptor": {"computedStyle": {"hideContentOnAmp": false, "hideContentOnDesktop": false, "hideContentOnHtml": false, "hideContentOnMobile": false}, "paragraph": {"computedStyle": {"linkColor": "#8a3b8f"}, "html": "<p style=\"word-break:break-word;\"><span><strong>CHRISTMAS UGLY SWEATER PACK</strong></span></p>", "style": {"color": "#393d47", "font-family": "inherit", "font-size": "15px", "letter-spacing": "0px", "line-height": "120%", "text-align": "center"}}, "style": {"padding-bottom": "0px", "padding-left": "15px", "padding-right": "15px", "padding-top": "10px"}}, "locked": false, "type": "mailup-bee-newsletter-modules-paragraph", "uuid": "4d126010-0f15-48df-9c44-047f41119ace"}, {"descriptor": {"computedStyle": {"hideContentOnAmp": false, "hideContentOnDesktop": false, "hideContentOnHtml": false, "hideContentOnMobile": false}, "paragraph": {"computedStyle": {"linkColor": "#8a3b8f"}, "html": "<p style=\"word-break:break-word;\"><span>Lorem impsum at</span></p>", "style": {"color": "#393d47", "font-family": "inherit", "font-size": "15px", "letter-spacing": "0px", "line-height": "120%", "text-align": "center"}}, "style": {"padding-bottom": "10px", "padding-left": "15px", "padding-right": "15px", "padding-top": "3px"}}, "locked": false, "type": "mailup-bee-newsletter-modules-paragraph", "uuid": "631851dc-f87a-4fd0-93a8-634de76537ec"}, {"descriptor": {"button": {"href": "example.com", "label": "<div class=\"txtTinyMce-wrapper\" style=\"\" data-mce-style=\"\"><p style=\"word-break:break-word;\" data-mce-style=\"word-break:break-word;\"><span style=\"\" data-mce-style=\"\"><strong>SHOP NOW</strong></span></p></div>", "style": {"background-color": "transparent", "border-bottom": "2px solid #B21420", "border-left": "2px solid #B21420", "border-radius": "0px", "border-right": "2px solid #B21420", "border-top": "2px solid #B21420", "color": "#b21420", "direction": "ltr", "font-family": "inherit", "font-size": "12px", "line-height": "150%", "max-width": "100%", "padding-bottom": "3px", "padding-left": "20px", "padding-right": "20px", "padding-top": "3px", "width": "auto"}, "target": "_self"}, "computedStyle": {"height": 34, "hideContentOnMobile": false, "width": 112}, "style": {"padding-bottom": "10px", "padding-left": "10px", "padding-right": "10px", "padding-top": "10px", "text-align": "center"}}, "locked": false, "type": "mailup-bee-newsletter-modules-button", "uuid": "7ee62d0b-650c-4e6d-a3b7-971f1f6a74f6"}], "style": {"background-color": "transparent", "border-bottom": "0px solid transparent", "border-left": "0px solid transparent", "border-right": "0px solid transparent", "border-top": "0px solid transparent", "padding-bottom": "0px", "padding-left": "0px", "padding-right": "0px", "padding-top": "0px"}, "uuid": "c7128cf6-3f6f-4121-bff8-f6c8b7511d28"}, {"grid-columns": 4, "modules": [{"descriptor": {"computedStyle": {"class": "center fixedwidth fullwidthOnMobile", "width": "170px"}, "image": {"alt": "Product", "height": "340px", "href": "", "prefix": "", "src": "https://d1oco4z2z1fhwp.cloudfront.net/templates/default/5706/AdobeStock_384985213_edited_1.jpg", "target": "_self", "width": "300px"}, "style": {"padding-bottom": "20px", "padding-left": "20px", "padding-right": "20px", "padding-top": "20px", "width": "100%"}}, "locked": false, "type": "mailup-bee-newsletter-modules-image", "uuid": "4fbebe84-1477-417e-bac1-11e462591a37"}, {"descriptor": {"computedStyle": {"hideContentOnAmp": false, "hideContentOnDesktop": false, "hideContentOnHtml": false, "hideContentOnMobile": false}, "paragraph": {"computedStyle": {"linkColor": "#8a3b8f"}, "html": "<p style=\"word-break:break-word;\"><span><strong>RED POLAR BEAR SWEATER</strong></span></p>", "style": {"color": "#393d47", "font-family": "inherit", "font-size": "15px", "letter-spacing": "0px", "line-height": "120%", "text-align": "center"}}, "style": {"padding-bottom": "0px", "padding-left": "15px", "padding-right": "15px", "padding-top": "10px"}}, "locked": false, "type": "mailup-bee-newsletter-modules-paragraph", "uuid": "d42d5ba8-5b48-4351-ad02-bd09a4978533"}, {"descriptor": {"computedStyle": {"hideContentOnAmp": false, "hideContentOnDesktop": false, "hideContentOnHtml": false, "hideContentOnMobile": false}, "paragraph": {"computedStyle": {"linkColor": "#8a3b8f"}, "html": "<p style=\"word-break:break-word;\"><span>Lorem impsum at</span></p>", "style": {"color": "#393d47", "font-family": "inherit", "font-size": "15px", "letter-spacing": "0px", "line-height": "120%", "text-align": "center"}}, "style": {"padding-bottom": "10px", "padding-left": "15px", "padding-right": "15px", "padding-top": "3px"}}, "locked": false, "type": "mailup-bee-newsletter-modules-paragraph", "uuid": "037a712e-f6e3-4b9d-901f-41c00a4c72d5"}, {"descriptor": {"button": {"href": "example.com", "label": "<div class=\"txtTinyMce-wrapper\" style=\"\" data-mce-style=\"\"><p style=\"word-break:break-word;\" data-mce-style=\"word-break:break-word;\"><span style=\"\" data-mce-style=\"\"><strong>SHOP NOW</strong></span></p></div>", "style": {"background-color": "transparent", "border-bottom": "2px solid #B21420", "border-left": "2px solid #B21420", "border-radius": "0px", "border-right": "2px solid #B21420", "border-top": "2px solid #B21420", "color": "#b21420", "direction": "ltr", "font-family": "inherit", "font-size": "12px", "line-height": "150%", "max-width": "100%", "padding-bottom": "3px", "padding-left": "20px", "padding-right": "20px", "padding-top": "3px", "width": "auto"}, "target": "_self"}, "computedStyle": {"height": 34, "hideContentOnMobile": false, "width": 112}, "style": {"padding-bottom": "10px", "padding-left": "10px", "padding-right": "10px", "padding-top": "10px", "text-align": "center"}}, "locked": false, "type": "mailup-bee-newsletter-modules-button", "uuid": "60c60130-5468-4ec0-9087-ff32d19a22c5"}], "style": {"background-color": "transparent", "border-bottom": "0px solid transparent", "border-left": "0px solid transparent", "border-right": "0px solid transparent", "border-top": "0px solid transparent", "padding-bottom": "0px", "padding-left": "0px", "padding-right": "0px", "padding-top": "0px"}, "uuid": "0563947f-e109-4bdc-8210-855da19de254"}], "container": {"style": {"background-color": "transparent", "background-image": "none", "background-position": "top left", "background-repeat": "no-repeat"}}, "content": {"computedStyle": {"hideContentOnDesktop": false, "hideContentOnMobile": false, "rowColStackOnMobile": true, "rowReverseColStackOnMobile": false, "verticalAlign": "top"}, "style": {"background-color": "#f3f3f3", "background-image": "none", "background-position": "top left", "background-repeat": "no-repeat", "color": "#000000", "width": "630px"}}, "empty": false, "locked": false, "synced": false, "type": "three-columns-empty", "uuid": "20694b27-0e4e-4d28-9ec2-a340c83d0234"}, {"columns": [{"grid-columns": 12, "modules": [{"descriptor": {"computedStyle": {"hideContentOnMobile": false}, "spacer": {"style": {"height": "60px"}}}, "locked": false, "type": "mailup-bee-newsletter-modules-spacer", "uuid": "7336c353-872d-4cdc-9fdb-bf7ee57c70cf"}, {"descriptor": {"computedStyle": {"height": 42, "width": 52}, "heading": {"style": {"color": "#b21420", "direction": "ltr", "font-family": "'Nunito', Arial, 'Helvetica Neue', Helvetica, sans-serif", "font-size": "20px", "font-weight": "normal", "letter-spacing": "1px", "line-height": "120%", "link-color": "#b21420", "text-align": "center"}, "text": "<strong>GET IN THE FESTIVE MOOD!</strong>", "title": "h1"}, "style": {"padding-bottom": "10px", "padding-left": "30px", "padding-right": "30px", "padding-top": "30px", "text-align": "center", "width": "100%"}}, "locked": false, "type": "mailup-bee-newsletter-modules-heading", "uuid": "9a050182-dc39-4b78-af93-011e04f779bd"}], "style": {"background-color": "transparent", "border-bottom": "0px solid transparent", "border-left": "0px solid transparent", "border-right": "0px solid transparent", "border-top": "0px solid transparent", "padding-bottom": "5px", "padding-left": "0px", "padding-right": "0px", "padding-top": "5px"}, "uuid": "a0c73836-e05f-4042-a714-a344401078d0"}], "container": {"style": {"background-color": "transparent", "background-image": "none", "background-position": "top left", "background-repeat": "no-repeat"}}, "content": {"computedStyle": {"hideContentOnDesktop": false, "hideContentOnMobile": false, "rowColStackOnMobile": true, "rowReverseColStackOnMobile": false, "verticalAlign": "top"}, "style": {"background-color": "#f3f3f3", "background-image": "none", "background-position": "top left", "background-repeat": "no-repeat", "color": "#000000", "width": "630px"}}, "empty": false, "locked": false, "synced": false, "type": "one-column-empty", "uuid": "98241560-0e4a-4cf7-b808-ae339642a52e"}, {"columns": [{"grid-columns": 4, "modules": [{"descriptor": {"computedStyle": {"class": "center fixedwidth fullwidthOnMobile", "width": "170px"}, "image": {"alt": "Product", "height": "300px", "href": "", "prefix": "", "src": "https://d1oco4z2z1fhwp.cloudfront.net/templates/default/5706/AdobeStock_99656362_edit.jpg", "target": "_self", "width": "300px"}, "style": {"padding-bottom": "20px", "padding-left": "20px", "padding-right": "20px", "padding-top": "20px", "width": "100%"}}, "locked": false, "type": "mailup-bee-newsletter-modules-image", "uuid": "c9f71fa6-0f38-4dd1-83ad-e67fa53715ef"}, {"descriptor": {"computedStyle": {"hideContentOnAmp": false, "hideContentOnDesktop": false, "hideContentOnHtml": false, "hideContentOnMobile": false}, "paragraph": {"computedStyle": {"linkColor": "#8a3b8f"}, "html": "<p style=\"word-break:break-word;\"><span><strong>PATTERN GLOVES</strong></span></p>", "style": {"color": "#393d47", "font-family": "inherit", "font-size": "15px", "letter-spacing": "0px", "line-height": "120%", "text-align": "center"}}, "style": {"padding-bottom": "0px", "padding-left": "15px", "padding-right": "15px", "padding-top": "10px"}}, "locked": false, "type": "mailup-bee-newsletter-modules-paragraph", "uuid": "9cb06277-e599-49d1-a4a9-d0498dfaed6a"}, {"descriptor": {"computedStyle": {"hideContentOnAmp": false, "hideContentOnDesktop": false, "hideContentOnHtml": false, "hideContentOnMobile": false}, "paragraph": {"computedStyle": {"linkColor": "#8a3b8f"}, "html": "<p style=\"word-break:break-word;\"><span>Lorem impsum at</span></p>", "style": {"color": "#393d47", "font-family": "inherit", "font-size": "15px", "letter-spacing": "0px", "line-height": "120%", "text-align": "center"}}, "style": {"padding-bottom": "10px", "padding-left": "15px", "padding-right": "15px", "padding-top": "3px"}}, "locked": false, "type": "mailup-bee-newsletter-modules-paragraph", "uuid": "ecac5625-f289-4b19-911f-9d36db1bebb9"}, {"descriptor": {"button": {"href": "example.com", "label": "<div class=\"txtTinyMce-wrapper\" style=\"\" data-mce-style=\"\"><p style=\"word-break:break-word;\" data-mce-style=\"word-break:break-word;\"><span style=\"\" data-mce-style=\"\"><strong>SHOP NOW</strong></span></p></div>", "style": {"background-color": "transparent", "border-bottom": "2px solid #B21420", "border-left": "2px solid #B21420", "border-radius": "0px", "border-right": "2px solid #B21420", "border-top": "2px solid #B21420", "color": "#b21420", "direction": "ltr", "font-family": "inherit", "font-size": "12px", "line-height": "150%", "max-width": "100%", "padding-bottom": "3px", "padding-left": "20px", "padding-right": "20px", "padding-top": "3px", "width": "auto"}, "target": "_self"}, "computedStyle": {"height": 34, "hideContentOnMobile": false, "width": 112}, "style": {"padding-bottom": "10px", "padding-left": "10px", "padding-right": "10px", "padding-top": "10px", "text-align": "center"}}, "locked": false, "type": "mailup-bee-newsletter-modules-button", "uuid": "6299caa8-096d-466c-bf74-a8ac52a5b4ea"}], "style": {"background-color": "transparent", "border-bottom": "0px solid transparent", "border-left": "0px solid transparent", "border-right": "0px solid transparent", "border-top": "0px solid transparent", "padding-bottom": "0px", "padding-left": "0px", "padding-right": "0px", "padding-top": "0px"}, "uuid": "674a2acb-aa03-411e-ae35-b564dcae1219"}, {"grid-columns": 4, "modules": [{"descriptor": {"computedStyle": {"class": "center fixedwidth fullwidthOnMobile", "width": "170px"}, "image": {"alt": "Product", "height": "300px", "href": "", "prefix": "", "src": "https://d1oco4z2z1fhwp.cloudfront.net/templates/default/5706/AdobeStock_237387028_edit2.jpg", "target": "_self", "width": "300px"}, "style": {"padding-bottom": "20px", "padding-left": "20px", "padding-right": "20px", "padding-top": "20px", "width": "100%"}}, "locked": false, "type": "mailup-bee-newsletter-modules-image", "uuid": "43b6a203-62d1-4d46-ab4a-86042c750c19"}, {"descriptor": {"computedStyle": {"hideContentOnAmp": false, "hideContentOnDesktop": false, "hideContentOnHtml": false, "hideContentOnMobile": false}, "paragraph": {"computedStyle": {"linkColor": "#8a3b8f"}, "html": "<p style=\"word-break:break-word;\"><span><strong>CHRISTMAS ANTLERS</strong></span></p>", "style": {"color": "#393d47", "font-family": "inherit", "font-size": "15px", "letter-spacing": "0px", "line-height": "120%", "text-align": "center"}}, "style": {"padding-bottom": "0px", "padding-left": "15px", "padding-right": "15px", "padding-top": "10px"}}, "locked": false, "type": "mailup-bee-newsletter-modules-paragraph", "uuid": "6b8dfdd3-67b2-42d8-a1b4-3fad29c66e2b"}, {"descriptor": {"computedStyle": {"hideContentOnAmp": false, "hideContentOnDesktop": false, "hideContentOnHtml": false, "hideContentOnMobile": false}, "paragraph": {"computedStyle": {"linkColor": "#8a3b8f"}, "html": "<p style=\"word-break:break-word;\"><span>Lorem impsum at</span></p>", "style": {"color": "#393d47", "font-family": "inherit", "font-size": "15px", "letter-spacing": "0px", "line-height": "120%", "text-align": "center"}}, "style": {"padding-bottom": "10px", "padding-left": "15px", "padding-right": "15px", "padding-top": "3px"}}, "locked": false, "type": "mailup-bee-newsletter-modules-paragraph", "uuid": "aeb87edb-7010-4ae0-83dd-f38f386c19a8"}, {"descriptor": {"button": {"href": "example.com", "label": "<div class=\"txtTinyMce-wrapper\" style=\"\" data-mce-style=\"\"><p style=\"word-break:break-word;\" data-mce-style=\"word-break:break-word;\"><span style=\"\" data-mce-style=\"\"><strong>SHOP NOW</strong></span></p></div>", "style": {"background-color": "transparent", "border-bottom": "2px solid #B21420", "border-left": "2px solid #B21420", "border-radius": "0px", "border-right": "2px solid #B21420", "border-top": "2px solid #B21420", "color": "#b21420", "direction": "ltr", "font-family": "inherit", "font-size": "12px", "line-height": "150%", "max-width": "100%", "padding-bottom": "3px", "padding-left": "20px", "padding-right": "20px", "padding-top": "3px", "width": "auto"}, "target": "_self"}, "computedStyle": {"height": 34, "hideContentOnMobile": false, "width": 112}, "style": {"padding-bottom": "10px", "padding-left": "10px", "padding-right": "10px", "padding-top": "10px", "text-align": "center"}}, "locked": false, "type": "mailup-bee-newsletter-modules-button", "uuid": "32832127-a475-4d9e-ad51-06b4b8f40109"}], "style": {"background-color": "transparent", "border-bottom": "0px solid transparent", "border-left": "0px solid transparent", "border-right": "0px solid transparent", "border-top": "0px solid transparent", "padding-bottom": "0px", "padding-left": "0px", "padding-right": "0px", "padding-top": "0px"}, "uuid": "c7128cf6-3f6f-4121-bff8-f6c8b7511d28"}, {"grid-columns": 4, "modules": [{"descriptor": {"computedStyle": {"class": "center fixedwidth fullwidthOnMobile", "width": "170px"}, "image": {"alt": "Product", "height": "300px", "href": "", "prefix": "", "src": "https://d1oco4z2z1fhwp.cloudfront.net/templates/default/5706/AdobeStock_121137587_edit.jpg", "target": "_self", "width": "300px"}, "style": {"padding-bottom": "20px", "padding-left": "20px", "padding-right": "20px", "padding-top": "20px", "width": "100%"}}, "locked": false, "type": "mailup-bee-newsletter-modules-image", "uuid": "54254986-2f2d-42df-9214-f06e7c1c0314"}, {"descriptor": {"computedStyle": {"hideContentOnAmp": false, "hideContentOnDesktop": false, "hideContentOnHtml": false, "hideContentOnMobile": false}, "paragraph": {"computedStyle": {"linkColor": "#8a3b8f"}, "html": "<p style=\"word-break:break-word;\"><span><strong>FESTIVE SOCKS PACK</strong></span></p>", "style": {"color": "#393d47", "font-family": "inherit", "font-size": "15px", "letter-spacing": "0px", "line-height": "120%", "text-align": "center"}}, "style": {"padding-bottom": "0px", "padding-left": "15px", "padding-right": "15px", "padding-top": "10px"}}, "locked": false, "type": "mailup-bee-newsletter-modules-paragraph", "uuid": "65be7560-2ee2-442c-9a53-c3b153323c76"}, {"descriptor": {"computedStyle": {"hideContentOnAmp": false, "hideContentOnDesktop": false, "hideContentOnHtml": false, "hideContentOnMobile": false}, "paragraph": {"computedStyle": {"linkColor": "#8a3b8f"}, "html": "<p style=\"word-break:break-word;\"><span>Lorem impsum at</span></p>", "style": {"color": "#393d47", "font-family": "inherit", "font-size": "15px", "letter-spacing": "0px", "line-height": "120%", "text-align": "center"}}, "style": {"padding-bottom": "10px", "padding-left": "15px", "padding-right": "15px", "padding-top": "3px"}}, "locked": false, "type": "mailup-bee-newsletter-modules-paragraph", "uuid": "97f04790-ee19-49c7-b7af-50b85f7c9e1e"}, {"descriptor": {"button": {"href": "example.com", "label": "<div class=\"txtTinyMce-wrapper\" style=\"\" data-mce-style=\"\"><p style=\"word-break:break-word;\" data-mce-style=\"word-break:break-word;\"><span style=\"\" data-mce-style=\"\"><strong>SHOP NOW</strong></span></p></div>", "style": {"background-color": "transparent", "border-bottom": "2px solid #B21420", "border-left": "2px solid #B21420", "border-radius": "0px", "border-right": "2px solid #B21420", "border-top": "2px solid #B21420", "color": "#b21420", "direction": "ltr", "font-family": "inherit", "font-size": "12px", "line-height": "150%", "max-width": "100%", "padding-bottom": "3px", "padding-left": "20px", "padding-right": "20px", "padding-top": "3px", "width": "auto"}, "target": "_self"}, "computedStyle": {"height": 34, "hideContentOnMobile": false, "width": 112}, "style": {"padding-bottom": "10px", "padding-left": "10px", "padding-right": "10px", "padding-top": "10px", "text-align": "center"}}, "locked": false, "type": "mailup-bee-newsletter-modules-button", "uuid": "c259034f-fe08-4402-b84b-0b2f0fd15f36"}], "style": {"background-color": "transparent", "border-bottom": "0px solid transparent", "border-left": "0px solid transparent", "border-right": "0px solid transparent", "border-top": "0px solid transparent", "padding-bottom": "0px", "padding-left": "0px", "padding-right": "0px", "padding-top": "0px"}, "uuid": "0563947f-e109-4bdc-8210-855da19de254"}], "container": {"style": {"background-color": "transparent", "background-image": "none", "background-position": "top left", "background-repeat": "no-repeat"}}, "content": {"computedStyle": {"hideContentOnDesktop": false, "hideContentOnMobile": false, "rowColStackOnMobile": true, "rowReverseColStackOnMobile": false, "verticalAlign": "top"}, "style": {"background-color": "#f3f3f3", "background-image": "none", "background-position": "top left", "background-repeat": "no-repeat", "color": "#000000", "width": "630px"}}, "empty": false, "locked": false, "metadata": {"category": 678137, "dateCreated": "2021-12-09T23:42:20.926540Z", "dateModified": "2021-12-09T23:42:20.926540Z", "description": "", "idParent": null, "name": "3 PRODUCTS", "slug": "3-products", "thumb_large": "https://pro-bee-beepro-thumbnails.s3.amazonaws.com/templates/saved-rows/53601/708074/d98187bf-db73-4149-9edf-183d8eaf0fc0_large.jpg", "thumb_medium": "https://pro-bee-beepro-thumbnails.s3.amazonaws.com/templates/saved-rows/53601/708074/d98187bf-db73-4149-9edf-183d8eaf0fc0_medium.jpg", "thumb_small": "https://pro-bee-beepro-thumbnails.s3.amazonaws.com/templates/saved-rows/53601/708074/d98187bf-db73-4149-9edf-183d8eaf0fc0_small.jpg", "uuid": "d98187bf-db73-4149-9edf-183d8eaf0fc0"}, "synced": false, "type": "three-columns-empty", "uuid": "d1aeb4f1-6f12-410c-b953-9241fa0a4412"}, {"columns": [{"grid-columns": 12, "modules": [{"descriptor": {"computedStyle": {"hideContentOnMobile": false}, "spacer": {"style": {"height": "45px"}}}, "locked": false, "type": "mailup-bee-newsletter-modules-spacer", "uuid": "a1c6ee93-b00c-4408-8b6f-ec61fded9cbd"}], "style": {"background-color": "transparent", "border-bottom": "0px solid transparent", "border-left": "0px solid transparent", "border-right": "0px solid transparent", "border-top": "0px solid transparent", "padding-bottom": "5px", "padding-left": "0px", "padding-right": "0px", "padding-top": "5px"}, "uuid": "a0c73836-e05f-4042-a714-a344401078d0"}], "container": {"style": {"background-color": "transparent", "background-image": "none", "background-position": "top left", "background-repeat": "no-repeat"}}, "content": {"computedStyle": {"hideContentOnDesktop": false, "hideContentOnMobile": false, "rowColStackOnMobile": true, "rowReverseColStackOnMobile": false, "verticalAlign": "top"}, "style": {"background-color": "#f3f3f3", "background-image": "none", "background-position": "top left", "background-repeat": "no-repeat", "color": "#000000", "width": "630px"}}, "empty": false, "locked": false, "synced": false, "type": "one-column-empty", "uuid": "625f7d12-e7f3-495a-b676-eb7ebb84837c"}, {"columns": [{"grid-columns": 6, "modules": [{"descriptor": {"computedStyle": {"class": "center fixedwidth fullwidthOnMobile", "width": "255px"}, "image": {"alt": "Dog sweaters", "height": "350px", "href": "", "prefix": "", "src": "https://d1oco4z2z1fhwp.cloudfront.net/templates/default/5706/karsten-winegeart-YzxeHEzBZ6I-unsplash_edit.jpg", "target": "_self", "width": "300px"}, "style": {"padding-bottom": "30px", "padding-left": "30px", "padding-right": "30px", "padding-top": "30px", "width": "100%"}}, "locked": false, "type": "mailup-bee-newsletter-modules-image", "uuid": "cd2d0815-e644-4f07-a16e-414611d21782"}], "style": {"background-color": "transparent", "border-bottom": "0px solid transparent", "border-left": "0px solid transparent", "border-right": "0px solid transparent", "border-top": "0px solid transparent", "padding-bottom": "5px", "padding-left": "0px", "padding-right": "0px", "padding-top": "0px"}, "uuid": "08526247-3695-44b0-bd3a-f137142fccb8"}, {"grid-columns": 6, "modules": [{"descriptor": {"computedStyle": {"hideContentOnMobile": false}, "spacer": {"style": {"height": "60px"}}}, "locked": false, "type": "mailup-bee-newsletter-modules-spacer", "uuid": "3c281423-a0b0-46dc-aa51-e6fdbbe39e98"}, {"descriptor": {"computedStyle": {"height": 42, "width": 52}, "heading": {"style": {"color": "#b21420", "direction": "ltr", "font-family": "'Nunito', Arial, 'Helvetica Neue', Helvetica, sans-serif", "font-size": "20px", "font-weight": "normal", "letter-spacing": "1px", "line-height": "120%", "link-color": "#b21420", "text-align": "left"}, "text": "<strong>PUPS IN STYLE &mdash;</strong>", "title": "h1"}, "style": {"padding-bottom": "0px", "padding-left": "15px", "padding-right": "30px", "padding-top": "7px", "text-align": "center", "width": "100%"}}, "locked": false, "type": "mailup-bee-newsletter-modules-heading", "uuid": "e97339db-a2ec-4bb6-8948-889a980b15dd"}, {"descriptor": {"computedStyle": {"height": 42, "width": 52}, "heading": {"style": {"color": "#b21420", "direction": "ltr", "font-family": "'Nunito', Arial, 'Helvetica Neue', Helvetica, sans-serif", "font-size": "20px", "font-weight": "normal", "letter-spacing": "0px", "line-height": "120%", "link-color": "#b21420", "text-align": "left"}, "text": "celebrate with them!", "title": "h1"}, "style": {"padding-bottom": "0px", "padding-left": "15px", "padding-right": "30px", "padding-top": "1px", "text-align": "center", "width": "100%"}}, "locked": false, "type": "mailup-bee-newsletter-modules-heading", "uuid": "7bf6ebf6-5985-4af4-8710-a67cf8d40cad"}, {"descriptor": {"computedStyle": {"hideContentOnAmp": false, "hideContentOnDesktop": false, "hideContentOnHtml": false, "hideContentOnMobile": false}, "paragraph": {"computedStyle": {"linkColor": "#8a3b8f"}, "html": "<p style=\"word-break:break-word;\">Lorem ipsum dolor sit amet, consectetur adipiscing elit, sed do eiusmod tempor incididunt ut labore.</p>", "style": {"color": "#393d47", "font-family": "inherit", "font-size": "14px", "letter-spacing": "0px", "line-height": "150%", "text-align": "left"}}, "style": {"padding-bottom": "15px", "padding-left": "15px", "padding-right": "30px", "padding-top": "15px"}}, "locked": false, "type": "mailup-bee-newsletter-modules-paragraph", "uuid": "0cb0210d-bf20-462f-b31c-c483ad468a37"}, {"descriptor": {"button": {"href": "example.com", "label": "<div class=\"txtTinyMce-wrapper\" style=\"\" data-mce-style=\"\"><p style=\"word-break:break-word;\" data-mce-style=\"word-break:break-word;\"><span style=\"\" data-mce-style=\"\"><strong>SHOP NOW</strong></span></p></div>", "style": {"background-color": "transparent", "border-bottom": "2px solid #B21420", "border-left": "2px solid #B21420", "border-radius": "0px", "border-right": "2px solid #B21420", "border-top": "2px solid #B21420", "color": "#b21420", "direction": "ltr", "font-family": "inherit", "font-size": "13px", "line-height": "150%", "max-width": "100%", "padding-bottom": "5px", "padding-left": "35px", "padding-right": "35px", "padding-top": "5px", "width": "auto"}, "target": "_self"}, "computedStyle": {"height": 38, "hideContentOnMobile": false, "width": 148}, "style": {"padding-bottom": "10px", "padding-left": "15px", "padding-right": "30px", "padding-top": "10px", "text-align": "left"}}, "locked": false, "type": "mailup-bee-newsletter-modules-button", "uuid": "d5fb4df4-1032-4f55-9df4-23b58b4b11b4"}], "style": {"background-color": "transparent", "border-bottom": "0px solid transparent", "border-left": "0px solid transparent", "border-right": "0px solid transparent", "border-top": "0px solid transparent", "padding-bottom": "5px", "padding-left": "0px", "padding-right": "0px", "padding-top": "0px"}, "uuid": "51aa9f6c-3d1c-4164-9572-c5f1a2c9f787"}], "container": {"style": {"background-color": "transparent", "background-image": "none", "background-position": "top left", "background-repeat": "no-repeat"}}, "content": {"computedStyle": {"hideContentOnDesktop": false, "hideContentOnMobile": false, "rowColStackOnMobile": false, "rowReverseColStackOnMobile": false, "verticalAlign": "top"}, "style": {"background-color": "#ffffff", "background-image": "none", "background-position": "top left", "background-repeat": "no-repeat", "color": "#000000", "width": "630px"}}, "empty": false, "locked": false, "metadata": {"category": 678137, "dateCreated": "2021-12-09T23:42:51.227699Z", "dateModified": "2021-12-09T23:42:51.227699Z", "description": "", "idParent": null, "name": "image + text", "slug": "image-text", "thumb_large": "https://pro-bee-beepro-thumbnails.s3.amazonaws.com/templates/saved-rows/53601/708074/19b01b99-ba01-4dae-85dc-b6f077da66a9_large.jpg", "thumb_medium": "https://pro-bee-beepro-thumbnails.s3.amazonaws.com/templates/saved-rows/53601/708074/19b01b99-ba01-4dae-85dc-b6f077da66a9_medium.jpg", "thumb_small": "https://pro-bee-beepro-thumbnails.s3.amazonaws.com/templates/saved-rows/53601/708074/19b01b99-ba01-4dae-85dc-b6f077da66a9_small.jpg", "uuid": "19b01b99-ba01-4dae-85dc-b6f077da66a9"}, "synced": false, "type": "two-columns-empty", "uuid": "a8d34609-41a3-45ec-902d-7a45854b9383"}, {"columns": [{"grid-columns": 12, "modules": [{"descriptor": {"computedStyle": {"class": "center fixedwidth fullwidthOnMobile", "width": "598.5px"}, "image": {"alt": "Christmas pattern", "height": "94px", "href": "", "prefix": "", "src": "https://d1oco4z2z1fhwp.cloudfront.net/templates/default/5706/PATTERN-03.png", "target": "_self", "width": "877px"}, "style": {"padding-bottom": "0px", "padding-left": "0px", "padding-right": "0px", "padding-top": "0px", "width": "100%"}}, "locked": false, "type": "mailup-bee-newsletter-modules-image", "uuid": "4ea06eb2-22f7-4961-92ff-4bfd03615701"}, {"descriptor": {"computedStyle": {"hideContentOnMobile": false}, "spacer": {"style": {"height": "45px"}}}, "locked": false, "type": "mailup-bee-newsletter-modules-spacer", "uuid": "15c31043-fff4-400a-8b97-40b5c2879747"}, {"descriptor": {"computedStyle": {"height": 42, "width": 52}, "heading": {"style": {"color": "#ffffff", "direction": "ltr", "font-family": "'Nunito', Arial, 'Helvetica Neue', Helvetica, sans-serif", "font-size": "21px", "font-weight": "normal", "letter-spacing": "1px", "line-height": "150%", "link-color": "#ffffff", "text-align": "center"}, "text": "BECAUSE IT'S THE SEASON OF GIVING, WE'RE DONATING 20% OF OUR SALES TO A GOOD CAUSE", "title": "h1"}, "style": {"padding-bottom": "10px", "padding-left": "40px", "padding-right": "40px", "padding-top": "10px", "text-align": "center", "width": "100%"}}, "locked": false, "type": "mailup-bee-newsletter-modules-heading", "uuid": "94898279-923f-4dde-a325-b4683dccaa41"}, {"descriptor": {"computedStyle": {"hideContentOnMobile": false}, "spacer": {"style": {"height": "45px"}}}, "locked": false, "type": "mailup-bee-newsletter-modules-spacer", "uuid": "65a8671d-df24-47dc-b524-fa0ac48bf037"}, {"descriptor": {"computedStyle": {"class": "center fixedwidth fullwidthOnMobile", "width": "598.5px"}, "image": {"alt": "Christmas pattern", "height": "94px", "href": "", "prefix": "", "src": "https://d1oco4z2z1fhwp.cloudfront.net/templates/default/5706/PATTERN-03.png", "target": "_self", "width": "877px"}, "style": {"padding-bottom": "0px", "padding-left": "0px", "padding-right": "0px", "padding-top": "0px", "width": "100%"}}, "locked": false, "type": "mailup-bee-newsletter-modules-image", "uuid": "ef9a449d-11c9-4522-8168-a7d19814ac2f"}], "style": {"background-color": "transparent", "border-bottom": "0px solid transparent", "border-left": "0px solid transparent", "border-right": "0px solid transparent", "border-top": "0px solid transparent", "padding-bottom": "10px", "padding-left": "0px", "padding-right": "0px", "padding-top": "10px"}, "uuid": "a0c73836-e05f-4042-a714-a344401078d0"}], "container": {"style": {"background-color": "transparent", "background-image": "none", "background-position": "top left", "background-repeat": "no-repeat"}}, "content": {"computedStyle": {"hideContentOnDesktop": false, "hideContentOnMobile": false, "rowColStackOnMobile": true, "rowReverseColStackOnMobile": false, "verticalAlign": "top"}, "style": {"background-color": "#0a5029", "background-image": "none", "background-position": "top left", "background-repeat": "no-repeat", "color": "#000000", "width": "630px"}}, "empty": false, "locked": false, "synced": false, "type": "one-column-empty", "uuid": "cb06d350-1b4f-4f1e-a6e5-24891a484be3"}, {"columns": [{"grid-columns": 12, "modules": [{"descriptor": {"computedStyle": {"hideContentOnMobile": false}, "spacer": {"style": {"height": "35px"}}}, "locked": false, "type": "mailup-bee-newsletter-modules-spacer", "uuid": "909f1e51-77b5-4408-8ce7-d04ae0e3221c"}, {"descriptor": {"computedStyle": {"height": 42, "width": 52}, "heading": {"style": {"color": "#b21420", "direction": "ltr", "font-family": "'Nunito', Arial, 'Helvetica Neue', Helvetica, sans-serif", "font-size": "20px", "font-weight": "normal", "letter-spacing": "1px", "line-height": "120%", "link-color": "#b21420", "text-align": "center"}, "text": "<strong>STAY IN TOUCH!</strong>", "title": "h1"}, "style": {"padding-bottom": "10px", "padding-left": "30px", "padding-right": "30px", "padding-top": "10px", "text-align": "center", "width": "100%"}}, "locked": false, "type": "mailup-bee-newsletter-modules-heading", "uuid": "d0780072-efb0-4a37-b744-9c05e48d661d"}], "style": {"background-color": "transparent", "border-bottom": "0px solid transparent", "border-left": "0px solid transparent", "border-right": "0px solid transparent", "border-top": "0px solid transparent", "padding-bottom": "5px", "padding-left": "0px", "padding-right": "0px", "padding-top": "5px"}, "uuid": "a0c73836-e05f-4042-a714-a344401078d0"}], "container": {"style": {"background-color": "transparent", "background-image": "none", "background-position": "top left", "background-repeat": "no-repeat"}}, "content": {"computedStyle": {"hideContentOnDesktop": false, "hideContentOnMobile": false, "rowColStackOnMobile": true, "rowReverseColStackOnMobile": false, "verticalAlign": "top"}, "style": {"background-color": "#f3f3f3", "background-image": "none", "background-position": "top left", "background-repeat": "no-repeat", "color": "#000000", "width": "630px"}}, "empty": false, "locked": false, "synced": false, "type": "one-column-empty", "uuid": "34c3a81f-a7b6-4caa-be62-eaac67aafaa9"}, {"columns": [{"grid-columns": 4, "modules": [{"descriptor": {"computedStyle": {"class": "center autowidth", "hideContentOnMobile": false, "width": "210px"}, "image": {"alt": "Instagram Post", "height": "300px", "href": "", "prefix": "", "src": "https://d1oco4z2z1fhwp.cloudfront.net/templates/default/5706/sweater3.jpg", "target": "_self", "width": "300px"}, "style": {"padding-bottom": "0px", "padding-left": "0px", "padding-right": "0px", "padding-top": "0px", "width": "100%"}}, "locked": false, "type": "mailup-bee-newsletter-modules-image", "uuid": "d67249a2-6df7-4c95-bf8f-7a89a99333b5"}, {"descriptor": {"computedStyle": {"class": "center autowidth", "hideContentOnMobile": false, "width": "210px"}, "image": {"alt": "Instagram Post", "height": "300px", "href": "", "prefix": "", "src": "https://d1oco4z2z1fhwp.cloudfront.net/templates/default/5706/nonresident-c4Gt0PtW7Ec-unsplash_edit.jpg", "target": "_self", "width": "300px"}, "style": {"padding-bottom": "0px", "padding-left": "0px", "padding-right": "0px", "padding-top": "0px", "width": "100%"}}, "locked": false, "type": "mailup-bee-newsletter-modules-image", "uuid": "af3451e2-b0a3-49f1-bfcd-671aec63f1b0"}], "style": {"background-color": "transparent", "border-bottom": "0px solid transparent", "border-left": "0px solid transparent", "border-right": "0px solid transparent", "border-top": "0px solid transparent", "padding-bottom": "5px", "padding-left": "0px", "padding-right": "0px", "padding-top": "5px"}, "uuid": "158dfa73-91cf-4d2a-abb0-ccc177c84be0"}, {"grid-columns": 4, "modules": [{"descriptor": {"computedStyle": {"class": "center autowidth", "hideContentOnMobile": false, "width": "210px"}, "image": {"alt": "Instagram Post", "height": "300px", "href": "", "prefix": "", "src": "https://d1oco4z2z1fhwp.cloudfront.net/templates/default/5706/stte-funn-dkZB1__ovU8-unsplash_edit.jpg", "target": "_self", "width": "300px"}, "style": {"padding-bottom": "0px", "padding-left": "0px", "padding-right": "0px", "padding-top": "0px", "width": "100%"}}, "locked": false, "type": "mailup-bee-newsletter-modules-image", "uuid": "c647643b-b970-4b50-81fc-0ab7798c3cc6"}, {"descriptor": {"computedStyle": {"class": "center autowidth", "hideContentOnMobile": false, "width": "210px"}, "image": {"alt": "Instagram Post", "height": "300px", "href": "", "prefix": "", "src": "https://d1oco4z2z1fhwp.cloudfront.net/templates/default/5706/karsten-winegeart-qbadM0DNF8Y-unsplash_edit.jpg", "target": "_self", "width": "300px"}, "style": {"padding-bottom": "0px", "padding-left": "0px", "padding-right": "0px", "padding-top": "0px", "width": "100%"}}, "locked": false, "type": "mailup-bee-newsletter-modules-image", "uuid": "53d5ba79-ae24-4af8-b8f4-516b78dfd53c"}], "style": {"background-color": "transparent", "border-bottom": "0px solid transparent", "border-left": "0px solid transparent", "border-right": "0px solid transparent", "border-top": "0px solid transparent", "padding-bottom": "5px", "padding-left": "0px", "padding-right": "0px", "padding-top": "5px"}, "uuid": "e20c20b3-6d03-45a3-a0e7-f58b7dbd257a"}, {"grid-columns": 4, "modules": [{"descriptor": {"computedStyle": {"class": "center autowidth", "hideContentOnMobile": false, "width": "210px"}, "image": {"alt": "Instagram Post", "height": "300px", "href": "", "prefix": "", "src": "https://d1oco4z2z1fhwp.cloudfront.net/templates/default/5706/STAMP-01-01_editj.png", "target": "_self", "width": "300px"}, "style": {"padding-bottom": "0px", "padding-left": "0px", "padding-right": "0px", "padding-top": "0px", "width": "100%"}}, "locked": false, "type": "mailup-bee-newsletter-modules-image", "uuid": "b6cb70fe-af83-4046-b457-4949c32d15b3"}, {"descriptor": {"computedStyle": {"class": "center autowidth", "hideContentOnMobile": false, "width": "210px"}, "image": {"alt": "Instagram Post", "height": "300px", "href": "", "prefix": "", "src": "https://d1oco4z2z1fhwp.cloudfront.net/templates/default/5706/sweater.jpg", "target": "_self", "width": "300px"}, "style": {"padding-bottom": "0px", "padding-left": "0px", "padding-right": "0px", "padding-top": "0px", "width": "100%"}}, "locked": false, "type": "mailup-bee-newsletter-modules-image", "uuid": "35152b12-fbf4-4724-9945-808b90fda94c"}], "style": {"background-color": "transparent", "border-bottom": "0px solid transparent", "border-left": "0px solid transparent", "border-right": "0px solid transparent", "border-top": "0px solid transparent", "padding-bottom": "5px", "padding-left": "0px", "padding-right": "0px", "padding-top": "5px"}, "uuid": "4eb1ce2d-ce44-450f-9a49-d9b4af9978d6"}], "container": {"style": {"background-color": "transparent", "background-image": "none", "background-position": "top left", "background-repeat": "no-repeat"}}, "content": {"computedStyle": {"hideContentOnDesktop": false, "hideContentOnMobile": false, "rowColStackOnMobile": false, "rowReverseColStackOnMobile": false, "verticalAlign": "top"}, "style": {"background-color": "#f3f3f3", "background-image": "none", "background-position": "top left", "background-repeat": "no-repeat", "color": "#000000", "width": "630px"}}, "empty": false, "locked": false, "synced": false, "type": "three-columns-empty", "uuid": "be7369dd-d87d-40b6-b55b-f582c4183254"}, {"columns": [{"grid-columns": 12, "modules": [{"descriptor": {"computedStyle": {"hideContentOnMobile": false}, "spacer": {"style": {"height": "25px"}}}, "locked": false, "type": "mailup-bee-newsletter-modules-spacer", "uuid": "e57a2f0d-310d-408f-9f2a-fa3b74464ec7"}, {"descriptor": {"button": {"href": "example.com", "label": "<div class=\"txtTinyMce-wrapper\" style=\"\" data-mce-style=\"\"><p style=\"word-break:break-word;\" data-mce-style=\"word-break:break-word;\"><span style=\"\" data-mce-style=\"\"><strong>FOLLOW US</strong></span></p></div>", "style": {"background-color": "transparent", "border-bottom": "2px solid #B21420", "border-left": "2px solid #B21420", "border-radius": "0px", "border-right": "2px solid #B21420", "border-top": "2px solid #B21420", "color": "#b21420", "direction": "ltr", "font-family": "inherit", "font-size": "14px", "line-height": "180%", "max-width": "100%", "padding-bottom": "3px", "padding-left": "40px", "padding-right": "40px", "padding-top": "3px", "width": "auto"}, "target": "_self"}, "computedStyle": {"height": 38, "hideContentOnMobile": false, "width": 166}, "style": {"padding-bottom": "10px", "padding-left": "10px", "padding-right": "10px", "padding-top": "10px", "text-align": "center"}}, "locked": false, "type": "mailup-bee-newsletter-modules-button", "uuid": "8b6e5f9a-e14f-4c54-9766-e45016202138"}, {"descriptor": {"computedStyle": {"hideContentOnMobile": false}, "spacer": {"style": {"height": "25px"}}}, "locked": false, "type": "mailup-bee-newsletter-modules-spacer", "uuid": "b0f28a1c-f090-4c0c-9729-83a4a776778d"}], "style": {"background-color": "transparent", "border-bottom": "0px solid transparent", "border-left": "0px solid transparent", "border-right": "0px solid transparent", "border-top": "0px solid transparent", "padding-bottom": "5px", "padding-left": "0px", "padding-right": "0px", "padding-top": "5px"}, "uuid": "a0c73836-e05f-4042-a714-a344401078d0"}], "container": {"style": {"background-color": "transparent", "background-image": "none", "background-position": "top left", "background-repeat": "no-repeat"}}, "content": {"computedStyle": {"hideContentOnDesktop": false, "hideContentOnMobile": false, "rowColStackOnMobile": true, "rowReverseColStackOnMobile": false, "verticalAlign": "top"}, "style": {"background-color": "#f3f3f3", "background-image": "none", "background-position": "top left", "background-repeat": "no-repeat", "color": "#000000", "width": "630px"}}, "empty": false, "locked": false, "synced": false, "type": "one-column-empty", "uuid": "f0f8ba76-81f6-4eda-8a05-90941dd0c09a"}, {"columns": [{"grid-columns": 12, "modules": [{"descriptor": {"computedStyle": {"align": "right", "hideContentOnMobile": false}, "divider": {"style": {"border-top": "1px solid #666666", "width": "100%"}}, "style": {"padding-bottom": "10px", "padding-left": "10px", "padding-right": "0px", "padding-top": "10px"}}, "locked": false, "type": "mailup-bee-newsletter-modules-divider", "uuid": "f38ebb3d-e8de-4733-a3aa-1fea18b833cd"}, {"descriptor": {"computedStyle": {"class": "center autowidth", "width": "80px"}, "image": {"alt": "Logo", "height": "49px", "href": "", "prefix": "", "src": "https://d1oco4z2z1fhwp.cloudfront.net/templates/default/5706/LOGO-02-02_02_1.png", "target": "_self", "width": "80px"}, "style": {"padding-bottom": "10px", "padding-left": "15px", "padding-right": "15px", "padding-top": "10px", "width": "100%"}}, "locked": false, "type": "mailup-bee-newsletter-modules-image", "uuid": "0fda1569-12d3-4342-8928-a56404db940e"}, {"align": "left", "descriptor": {"computedStyle": {"height": 37, "hideContentOnMobile": false, "iconsDefaultWidth": 32, "padding": "0 5px 0 5px", "width": 198}, "iconsList": {"icons": [{"image": {"alt": "Facebook", "href": "https://www.facebook.com", "prefix": "https://www.facebook.com", "src": "https://app-rsrc.getbee.io/public/resources/social-networks-icon-sets/t-outline-circle-dark-gray/facebook@2x.png", "target": "_self", "title": "Facebook"}, "name": "facebook", "text": "", "type": "follow"}, {"image": {"alt": "Twitter", "href": "https://www.twitter.com", "prefix": "https://www.twitter.com", "src": "https://app-rsrc.getbee.io/public/resources/social-networks-icon-sets/t-outline-circle-dark-gray/twitter@2x.png", "target": "_self", "title": "Twitter"}, "name": "twitter", "text": "", "type": "follow"}, {"image": {"alt": "Instagram", "href": "https://www.instagram.com", "prefix": "https://www.instagram.com", "src": "https://app-rsrc.getbee.io/public/resources/social-networks-icon-sets/t-outline-circle-dark-gray/instagram@2x.png", "target": "_self", "title": "Instagram"}, "name": "instagram", "text": "", "type": "follow"}]}, "style": {"padding-bottom": "5px", "padding-left": "20px", "padding-right": "20px", "padding-top": "10px", "text-align": "center"}}, "locked": false, "type": "mailup-bee-newsletter-modules-social", "uuid": "b3cd7f1e-2946-411b-a390-33512af413e9"}, {"descriptor": {"computedStyle": {"hideContentOnAmp": false, "hideContentOnDesktop": false, "hideContentOnHtml": false, "hideContentOnMobile": false}, "paragraph": {"computedStyle": {"linkColor": "#b21420"}, "html": "<p style=\"word-break:break-word;\"><strong><span style=\"color:#39374e;\"><a href=\"example.com\" target=\"_blank\" style=\"text-decoration: none;\" rel=\"noopener\">Delivery Information</a>&nbsp; &nbsp;|&nbsp; &nbsp;<a href=\"example.com\" target=\"_blank\" style=\"text-decoration: none;\" rel=\"noopener\">About Us</a>&nbsp; &nbsp;|&nbsp; &nbsp;<a href=\"example.com\" target=\"_blank\" style=\"text-decoration: none;\" rel=\"noopener\">Contact</a></span></strong></p>", "style": {"color": "#666666", "font-family": "inherit", "font-size": "12px", "line-height": "120%", "text-align": "center"}}, "style": {"padding-bottom": "5px", "padding-left": "10px", "padding-right": "10px", "padding-top": "15px"}}, "locked": false, "type": "mailup-bee-newsletter-modules-paragraph", "uuid": "9e8ccdfb-2a99-465c-9ac2-121a3b8d85df"}, {"descriptor": {"computedStyle": {"hideContentOnAmp": false, "hideContentOnDesktop": false, "hideContentOnHtml": false, "hideContentOnMobile": false}, "paragraph": {"computedStyle": {"linkColor": "#b21420"}, "html": "<p style=\"word-break:break-word;\"><span style=\"color:#39374e;\">&nbsp;Changed your mind? You can </span><strong><span><code data-bee-code=\"\" data-bee-type=\"speciallink\"><a href=\"*|UNSUB|*\" target=\"_blank\" rel=\"noopener\">unsubscribe</a></code></span></strong><span style=\"color:#39374e;\"><strong> </strong>at any time.</span></p>", "style": {"color": "#666666", "font-family": "inherit", "font-size": "12px", "line-height": "120%", "text-align": "center"}}, "style": {"padding-bottom": "15px", "padding-left": "10px", "padding-right": "10px", "padding-top": "5px"}}, "locked": false, "type": "mailup-bee-newsletter-modules-paragraph", "uuid": "693fe523-da33-427f-be81-bef0cd99075f"}, {"descriptor": {"computedStyle": {"hideContentOnMobile": false}, "spacer": {"style": {"height": "35px"}}}, "locked": false, "type": "mailup-bee-newsletter-modules-spacer", "uuid": "376fa1f2-d583-4cef-958f-b19a7189c03a"}], "style": {"background-color": "transparent", "border-bottom": "0px solid transparent", "border-left": "0px solid transparent", "border-right": "0px solid transparent", "border-top": "0px solid transparent", "padding-bottom": "5px", "padding-left": "0px", "padding-right": "0px", "padding-top": "15px"}, "uuid": "f5eb2219-b13e-43fb-a2d0-75f9397c9d0f"}], "container": {"style": {"background-color": "transparent", "background-image": "none", "background-position": "top left", "background-repeat": "no-repeat"}}, "content": {"computedStyle": {"hideContentOnDesktop": false, "hideContentOnMobile": false, "linkColor": "#000000", "messageBackgroundColor": "#000000", "rowColStackOnMobile": false, "rowReverseColStackOnMobile": false, "verticalAlign": "top"}, "style": {"background-color": "#f3f3f3", "background-image": "none", "background-position": "top left", "background-repeat": "no-repeat", "color": "#000000", "width": "630px"}}, "empty": false, "locked": false, "synced": false, "type": "one-column-empty", "uuid": "347e811f-2c47-4439-929b-4d528fdeb239"}], "template": {"name": "template-base", "type": "basic", "version": "2.0.0"}, "title": ""}}